wiperf_poller/__init__.py
wiperf_poller/__main__.py
wiperf_poller/config/__init__.py
wiperf_poller/config/general.py
wiperf_poller/config/utils.py
wiperf_poller/exporters/__init__.py
wiperf_poller/exporters/cacheexporter.py
wiperf_poller/exporters/exportresults.py
wiperf_poller/exporters/influxexporter.py
wiperf_poller/exporters/influxexporter2.py
wiperf_poller/exporters/splunkexporter.py
wiperf_poller/exporters/spoolexporter.py
wiperf_poller/helpers/__init__.py
wiperf_poller/helpers/bouncer.py
wiperf_poller/helpers/config.py
wiperf_poller/helpers/error_messages.py
wiperf_poller/helpers/ethernetadapter.py
wiperf_poller/helpers/fieldchecker.py
wiperf_poller/helpers/filelogger.py
wiperf_poller/helpers/lockfile.py
wiperf_poller/helpers/os_cmds.py
wiperf_poller/helpers/poll_status.py
wiperf_poller/helpers/remoteconfig.py
wiperf_poller/helpers/route.py
wiperf_poller/helpers/statusfile.py
wiperf_poller/helpers/timefunc.py
wiperf_poller/helpers/watchdog.py
wiperf_poller/helpers/wirelessadapter.py
wiperf_poller/testers/__init__.py
wiperf_poller/testers/dhcptester.py
wiperf_poller/testers/dnstester.py
wiperf_poller/testers/ethernetconnectiontester.py
wiperf_poller/testers/httptester.py
wiperf_poller/testers/iperf3tester.py
wiperf_poller/testers/mgtconnectiontester.py
wiperf_poller/testers/pingtester.py
wiperf_poller/testers/smbtester.py
wiperf_poller/testers/speedtester.py
wiperf_poller/testers/wifiauthentication.py
wiperf_poller/testers/wirelessconnectiontester.py
wiperf_poller-0.3.6.dist-info/LICENSE
wiperf_poller-0.3.6.dist-info/METADATA
wiperf_poller-0.3.6.dist-info/WHEEL
wiperf_poller-0.3.6.dist-info/entry_points.txt
wiperf_poller-0.3.6.dist-info/top_level.txt
wiperf_poller-0.3.6.dist-info/RECORD
