Metadata-Version: 2.1
Name: wiperf-poller
Version: 0.3.6
Summary: Poller for the wiperf utlity
Home-page: https://github.com/wifinigel/wiperf_poller
Author: Nigel Bowden
Author-email: wifinigel@gmail.com
License: UNKNOWN
Platform: UNKNOWN
Classifier: Programming Language :: Python :: 3
Classifier: License :: Free for non-commercial use
Classifier: Operating System :: POSIX :: Linux
Requires-Python: >=3.6
License-File: LICENSE
Requires-Dist: speedtest-cli
Requires-Dist: influxdb
Requires-Dist: influxdb-client
Requires-Dist: iperf3
Requires-Dist: timeout-decorator
